loggy/__init__.py
loggy/crypto.py
loggy/loggy.py
loggy/metrics.py
loggy/middleware.py
loggy/tracing.py
loggydev_py-0.1.3.dist-info/METADATA
loggydev_py-0.1.3.dist-info/WHEEL
loggydev_py-0.1.3.dist-info/top_level.txt
loggydev_py-0.1.3.dist-info/RECORD
