Metadata-Version: 2.4
Name: loggydev-py
Version: 0.1.3
Summary: A lightweight logger with remote logging, metrics, and distributed tracing for Python applications
Author-email: Kevin Wynn <kevin@loggy.dev>
License: ISC
Project-URL: Homepage, https://loggy.dev
Project-URL: Documentation, https://loggy.dev/docs
Project-URL: Repository, https://github.com/loggy-dev/loggy-py
Project-URL: Issues, https://github.com/loggy-dev/loggy-py/issues
Keywords: logs,logging,console,debug,logger,metrics,tracing,observability,monitoring
Classifier: Development Status :: 4 - Beta
Classifier: Intended Audience :: Developers
Classifier: License :: OSI Approved :: ISC License (ISCL)
Classifier: Operating System :: OS Independent
Classifier: Programming Language :: Python :: 3
Classifier: Programming Language :: Python :: 3.9
Classifier: Programming Language :: Python :: 3.10
Classifier: Programming Language :: Python :: 3.11
Classifier: Programming Language :: Python :: 3.12
Classifier: Topic :: Software Development :: Libraries :: Python Modules
Classifier: Topic :: System :: Logging
Classifier: Topic :: System :: Monitoring
Requires-Python: >=3.9
Requires-Dist: requests>=2.25.0
Requires-Dist: cryptography>=3.4.0
Provides-Extra: color
Requires-Dist: colorama>=0.4.4; extra == "color"
Provides-Extra: flask
Requires-Dist: flask>=2.0.0; extra == "flask"
Provides-Extra: fastapi
Requires-Dist: fastapi>=0.68.0; extra == "fastapi"
Requires-Dist: starlette>=0.14.0; extra == "fastapi"
Provides-Extra: all
Requires-Dist: colorama>=0.4.4; extra == "all"
Requires-Dist: flask>=2.0.0; extra == "all"
Requires-Dist: fastapi>=0.68.0; extra == "all"
Requires-Dist: starlette>=0.14.0; extra == "all"
Provides-Extra: dev
Requires-Dist: pytest>=7.0.0; extra == "dev"
Requires-Dist: pytest-asyncio>=0.20.0; extra == "dev"
Requires-Dist: black>=22.0.0; extra == "dev"
Requires-Dist: mypy>=0.990; extra == "dev"
Requires-Dist: ruff>=0.0.200; extra == "dev"
